README.md
setup.py
bbk.smartImage.egg-info/PKG-INFO
bbk.smartImage.egg-info/SOURCES.txt
bbk.smartImage.egg-info/dependency_links.txt
bbk.smartImage.egg-info/requires.txt
bbk.smartImage.egg-info/top_level.txt
smartImage/__init__.py
smartImage/nonMaxSuppression.py