Metadata-Version: 1.1
Name: bbk.smartImage
Version: 1.5
Summary: Smart Image Processing Tools...
Home-page: https://github.com/babiking/PyPi_Tools/smartImage
Author: babiking
Author-email: brojackfeely@163.com
License: LICENSE
Platform: UNKNOWN
Classifier: Programming Language :: Python :: 2.7
Classifier: Programming Language :: Python :: 3.6
Classifier: Topic :: Scientific/Engineering :: Image Recognition
